{
  "id": "meadowsweet",
  "nameEn": "Meadowsweet",
  "nameDe": "Mädesüß",
  "scientificName": "Filipendula ulmaria",
  "family": "Rosaceae",
  "kind": "herb",
  "countryIds": [
    "at",
    "de",
    "gb",
    "pl",
    "se",
    "ie"
  ],
  "partsUsed": "Flowering tops (traditionally employed botanical drug part)",
  "partsUsedDe": "Blühende Spitzen",
  "habitat": "Damp meadows and ditches of Europe.",
  "habitatDe": "Damp Wiesen und ditches von Europa.",
  "traditionalUsesEn": "Traditional anti-inflammatory tea; historical salicylate plant (aspirin story).",
  "traditionalUsesDe": "Traditionell anti-entzündlich Tee; historisch salicylate Pflanze (aspirin story).",
  "activeCompounds": "Salicylates, flavonoids, tannins.",
  "activeCompoundsDe": "Salicylates, Flavonoide, tannins.",
  "preparation": "Flower infusion; flowering herb tea as needed. Usual tea amounts.",
  "preparationDe": "Aufguss aus den Blüten; bei Bedarf auch blühendes Kraut. Übliche Teemengen.",
  "cautions": "Salicylate sensitivity / anticoagulant interactions possible.",
  "cautionsDe": "Salicylate sensitivity / anticoagulant interactions möglich.",
  "floweringSeason": "June–September",
  "floweringSeasonDe": "Juni–September",
  "historicalNotes": "Linked to early aspirin research; fragrant marsh herb.",
  "historicalNotesDe": "Linked zu früh aspirin research; fragrant marsh Kraut.",
  "useCategoryIds": [
    "anti-inflammatory",
    "pain-relief",
    "digestive"
  ],
  "bloomSeasons": [
    "summer",
    "autumn"
  ]
}
