{
  "id": "wasabi",
  "countryIds": [
    "jp"
  ],
  "nameEn": "Wasabi",
  "nameDe": "Wasabi",
  "scientificName": "Eutrema japonicum (syn. Wasabia japonica)",
  "family": "Brassicaceae",
  "partsUsed": "Rhizome (botanical part traditionally employed)",
  "habitat": "Cool mountain streams of Japan; difficult cultivation.",
  "traditionalUsesEn": "Culinary pungent condiment; traditional Japanese accompaniment to raw fish.",
  "traditionalUsesDe": "Scharfes Würzmittel der japanischen Küche; traditionell bei Fischgerichten.",
  "activeCompounds": "Isothiocyanates (allyl isothiocyanate related compounds from glucosinolates)",
  "preparation": "Freshly grated rhizome; many commercial pastes are horseradish-based substitutes.",
  "cautions": "Pungent vapors irritate eyes and sinuses. Food use only.",
  "floweringSeason": "Unknown (cultivated)",
  "historicalNotes": "True wasabi scarce and prized; often replaced by dyed horseradish abroad.",
  "partsUsedDe": "Rhizom und Stängelbasis.",
  "habitatDe": "Kühle Bergbäche Japans; echte Wasabi-Kultur anspruchsvoll.",
  "activeCompoundsDe": "Isothiocyanate (Allylisothiocyanat und verwandte)",
  "preparationDe": "Frisch geriebener Rhizomstamm; viele „Wasabi“-Produkte sind Meerrettich-Mischungen.",
  "cautionsDe": "Scharf – Augen und Nase reizen. Lebensmittelverwendung.",
  "floweringSeasonDe": "Unbekannt (Kultur)",
  "historicalNotesDe": "Japanische Bergbach-Kulturpflanze; teures Echtes oft durch Meerrettich ersetzt.",
  "useCategoryIds": [
    "culinary"
  ],
  "bloomSeasons": [
    "yearRound"
  ]
}
